src/__init__.py
src/cli.py
src/config.py
src/llama_server.py
src/llm.py
src/main.py
src/models_registry.py
src/npc_chat.py
src/steam.py
src/term_ui.py
src/tunnel.py
src/wizard.py
loreguard_cli-0.3.2.dist-info/METADATA
loreguard_cli-0.3.2.dist-info/WHEEL
loreguard_cli-0.3.2.dist-info/entry_points.txt
loreguard_cli-0.3.2.dist-info/licenses/LICENSE
loreguard_cli-0.3.2.dist-info/RECORD
