Metadata-Version: 2.4
Name: loreguard-cli
Version: 0.3.2
Summary: Local inference client for Loreguard NPCs
Project-URL: Homepage, https://loreguard.com
Project-URL: Documentation, https://github.com/beyond-logic-labs/loreguard-cli#readme
Project-URL: Repository, https://github.com/beyond-logic-labs/loreguard-cli
Project-URL: Issues, https://github.com/beyond-logic-labs/loreguard-cli/issues
License-Expression: MIT
License-File: LICENSE
Keywords: gamedev,inference,llm,loreguard,npc
Classifier: Development Status :: 4 - Beta
Classifier: Environment :: Console
Classifier: Intended Audience :: Developers
Classifier: License :: OSI Approved :: MIT License
Classifier: Operating System :: OS Independent
Classifier: Programming Language :: Python :: 3.10
Classifier: Programming Language :: Python :: 3.11
Classifier: Programming Language :: Python :: 3.12
Classifier: Topic :: Games/Entertainment
Requires-Python: >=3.10
Requires-Dist: aiofiles>=24.1.0
Requires-Dist: httpx>=0.26.0
Requires-Dist: pydantic>=2.5.0
Requires-Dist: websockets>=12.0
Provides-Extra: build
Requires-Dist: pyinstaller>=6.0.0; extra == 'build'
Provides-Extra: dev
Requires-Dist: pytest-asyncio>=0.23.0; extra == 'dev'
Requires-Dist: pytest>=7.4.0; extra == 'dev'
Requires-Dist: ruff>=0.1.0; extra == 'dev'
